{
  "239867782567559169": {
    "username": "tisanecourte",
    "avatar": "9d102d4613a0655cdcbf2abc92b11a70"
  },
  "696766305101021194": {
    "username": "ungrandfan_",
    "avatar": "5b0c53a15ea41c57573ea83f580de9ba"
  },
  "760269183031836684": {
    "username": "seigneurnemesis",
    "avatar": "27b23ae1a5bb07c329a219fce007321b"
  },
  "1361814158529527930": {
    "username": "LOL PAS TROP FR",
    "avatar": "5c9e098c1858e30364e94bd87417f7f9"
  },
  "684773505157431347": {
    "username": "FlaviBot",
    "avatar": "a_521d1afb63e630ee2baabc76d9a3b723"
  },
  "347353755475509251": {
    "username": "smirefoof",
    "avatar": "c1cf83e6dde7778a153a76765bca8896"
  },
  "1230824879385743361": {
    "username": "milwep",
    "avatar": "2c4e7afd51e1e64d8251964cdf101d96"
  }
}